{
  "$schema": "https://developer.microsoft.com/json-schemas/fabric/item/report/definition/visualContainer/2.6.0/schema.json",
  "name": "a7c5b2d9f1840e63c2ab",
  "position": {
    "x": 320,
    "y": 332,
    "z": 15000,
    "height": 320,
    "width": 540,
    "tabOrder": 22000
  },
  "visual": {
    "visualType": "lineChart",
    "query": {
      "queryState": {
        "Category": {
          "projections": [
            {
              "field": {
                "Column": {
                  "Expression": {
                    "SourceRef": {
                      "Entity": "Date"
                    }
                  },
                  "Property": "MonthName"
                }
              },
              "queryRef": "Date.MonthName",
              "nativeQueryRef": "MonthName",
              "active": true
            }
          ]
        },
        "Tooltips": {
          "projections": [
            {
              "field": {
                "Aggregation": {
                  "Expression": {
                    "Column": {
                      "Expression": {
                        "SourceRef": {
                          "Entity": "Date"
                        }
                      },
                      "Property": "MonthNumber"
                    }
                  },
                  "Function": 4
                }
              },
              "queryRef": "Max(Date.MonthNumber)",
              "nativeQueryRef": " MonthNumber"
            }
          ]
        },
        "Y": {
          "projections": [
            {
              "field": {
                "Measure": {
                  "Expression": {
                    "SourceRef": {
                      "Entity": "Measure"
                    }
                  },
                  "Property": "Total Sales"
                }
              },
              "queryRef": "Measure.Total Sales",
              "nativeQueryRef": "Total Sales"
            }
          ]
        }
      },
      "sortDefinition": {
        "sort": [
          {
            "field": {
              "Aggregation": {
                "Expression": {
                  "Column": {
                    "Expression": {
                      "SourceRef": {
                        "Entity": "Date"
                      }
                    },
                    "Property": "MonthNumber"
                  }
                },
                "Function": 4
              }
            },
            "direction": "Ascending"
          }
        ]
      }
    },
    "objects": {
      "labels": [
        {
          "properties": {
            "show": {
              "expr": {
                "Literal": {
                  "Value": "false"
                }
              }
            }
          }
        }
      ],
      "valueAxis": [
        {
          "properties": {
            "start": {
              "expr": {
                "Literal": {
                  "Value": "0D"
                }
              }
            },
            "labelDisplayUnits": {
              "expr": {
                "Literal": {
                  "Value": "1000D"
                }
              }
            },
            "showAxisTitle": {
              "expr": {
                "Literal": {
                  "Value": "false"
                }
              }
            },
            "fontSize": {
              "expr": {
                "Literal": {
                  "Value": "8D"
                }
              }
            },
            "italic": {
              "expr": {
                "Literal": {
                  "Value": "false"
                }
              }
            },
            "fontFamily": {
              "expr": {
                "Literal": {
                  "Value": "'wf_standard-font_light, helvetica, arial, sans-serif'"
                }
              }
            }
          }
        }
      ],
      "dataPoint": [
        {
          "properties": {
            "fill": {
              "solid": {
                "color": {
                  "expr": {
                    "Measure": {
                      "Expression": {
                        "SourceRef": {
                          "Entity": "Measure"
                        }
                      },
                      "Property": "Sales Color"
                    }
                  }
                }
              }
            }
          },
          "selector": {
            "data": [
              {
                "dataViewWildcard": {
                  "matchingOption": 1
                }
              }
            ]
          }
        },
        {
          "properties": {
            "fill": {
              "solid": {
                "color": {
                  "expr": {
                    "Literal": {
                      "Value": "'#1E88E5'"
                    }
                  }
                }
              }
            }
          },
          "selector": {
            "metadata": "Measure.Total Sales"
          }
        },
        {
          "properties": {}
        }
      ],
      "categoryAxis": [
        {
          "properties": {
            "fontFamily": {
              "expr": {
                "Literal": {
                  "Value": "'wf_standard-font_light, helvetica, arial, sans-serif'"
                }
              }
            },
            "fontSize": {
              "expr": {
                "Literal": {
                  "Value": "8D"
                }
              }
            }
          }
        }
      ],
      "referenceLine": [
        {
          "properties": {
            "show": {
              "expr": {
                "Literal": {
                  "Value": "true"
                }
              }
            },
            "displayName": {
              "expr": {
                "Literal": {
                  "Value": "'Avg'"
                }
              }
            },
            "value": {
              "expr": {
                "Aggregation": {
                  "Expression": {
                    "SelectRef": {
                      "ExpressionName": "Measure.Total Sales"
                    }
                  },
                  "Function": 1
                }
              }
            },
            "lineColor": {
              "solid": {
                "color": {
                  "expr": {
                    "Literal": {
                      "Value": "'#7984EE'"
                    }
                  }
                }
              }
            },
            "width": {
              "expr": {
                "Literal": {
                  "Value": "1D"
                }
              }
            },
            "dataLabelShow": {
              "expr": {
                "Literal": {
                  "Value": "true"
                }
              }
            },
            "shadeShow": {
              "expr": {
                "Literal": {
                  "Value": "false"
                }
              }
            },
            "dataLabelText": {
              "expr": {
                "Literal": {
                  "Value": "'ValueAndName'"
                }
              }
            },
            "dataLabelColor": {
              "solid": {
                "color": {
                  "expr": {
                    "ThemeDataColor": {
                      "ColorId": 7,
                      "Percent": 0.2
                    }
                  }
                }
              }
            },
            "dataLabelDisplayUnits": {
              "expr": {
                "Literal": {
                  "Value": "1000D"
                }
              }
            },
            "dataLabelDecimalPoints": {
              "expr": {
                "Literal": {
                  "Value": "0D"
                }
              }
            }
          },
          "selector": {
            "metadata": "Measure.Total Sales",
            "id": "1"
          }
        }
      ],
      "error": [
        {
          "properties": {
            "enabled": {
              "expr": {
                "Literal": {
                  "Value": "false"
                }
              }
            }
          },
          "selector": {
            "metadata": "Measure.Total Sales"
          }
        },
        {
          "properties": {
            "errorRange": {
              "kind": "ErrorRange",
              "percentage": {
                "lowerBoundDelta": {
                  "expr": {
                    "Literal": {
                      "Value": "0.1D"
                    }
                  }
                },
                "upperBoundDelta": {
                  "expr": {
                    "Literal": {
                      "Value": "0.1D"
                    }
                  }
                }
              }
            }
          },
          "selector": {
            "data": [
              {
                "dataViewWildcard": {
                  "matchingOption": 0
                }
              }
            ],
            "metadata": "Measure.Total Sales",
            "highlightMatching": 1
          }
        }
      ],
      "zoom": [
        {
          "properties": {
            "show": {
              "expr": {
                "Literal": {
                  "Value": "false"
                }
              }
            }
          }
        }
      ]
    },
    "visualContainerObjects": {
      "title": [
        {
          "properties": {
            "text": {
              "expr": {
                "Literal": {
                  "Value": "'Curva de Gasto no Tempo (Cruzamentos)'"
                }
              }
            },
            "fontFamily": {
              "expr": {
                "Literal": {
                  "Value": "'''Segoe UI'', wf_segoe-ui_normal, helvetica, arial, sans-serif'"
                }
              }
            },
            "fontSize": {
              "expr": {
                "Literal": {
                  "Value": "10D"
                }
              }
            },
            "show": {
              "expr": {
                "Literal": {
                  "Value": "true"
                }
              }
            }
          }
        }
      ],
      "visualTooltip": [
        {
          "properties": {
            "section": {
              "expr": {
                "Literal": {
                  "Value": "'8e2ff8080e86a76d805f'"
                }
              }
            }
          }
        }
      ]
    },
    "drillFilterOtherVisuals": true
  }
}
