{
  "$schema": "https://developer.microsoft.com/json-schemas/fabric/item/report/definition/visualContainer/2.6.0/schema.json",
  "name": "5715f23ae7323c710a25",
  "position": {
    "x": 0,
    "y": 29.719153130905728,
    "z": 1000,
    "height": 158.22266450676307,
    "width": 288.72180451127821,
    "tabOrder": 1000
  },
  "visual": {
    "visualType": "clusteredBarChart",
    "query": {
      "queryState": {
        "Category": {
          "projections": [
            {
              "field": {
                "Column": {
                  "Expression": {
                    "SourceRef": {
                      "Entity": "DimPeritos"
                    }
                  },
                  "Property": "PeritoLabel"
                }
              },
              "queryRef": "DimPeritos.PeritoLabel",
              "nativeQueryRef": "PeritoLabel",
              "active": true
            }
          ]
        },
        "Y": {
          "projections": [
            {
              "field": {
                "Measure": {
                  "Expression": {
                    "SourceRef": {
                      "Entity": "Measure"
                    }
                  },
                  "Property": "Total Sales"
                }
              },
              "queryRef": "Measure.Total Sales",
              "nativeQueryRef": "Total Sales"
            }
          ]
        }
      },
      "sortDefinition": {
        "sort": [
          {
            "field": {
              "Measure": {
                "Expression": {
                  "SourceRef": {
                    "Entity": "Measure"
                  }
                },
                "Property": "Total Sales"
              }
            },
            "direction": "Descending"
          }
        ],
        "isDefaultSort": true
      }
    },
    "objects": {
      "dataPoint": [
        {
          "properties": {
            "fill": {
              "solid": {
                "color": {
                  "expr": {
                    "Literal": {
                      "Value": "'#1E88E5'"
                    }
                  }
                }
              }
            }
          }
        }
      ],
      "valueAxis": [
        {
          "properties": {
            "showAxisTitle": {
              "expr": {
                "Literal": {
                  "Value": "false"
                }
              }
            }
          }
        }
      ],
      "categoryAxis": [
        {
          "properties": {
            "showAxisTitle": {
              "expr": {
                "Literal": {
                  "Value": "false"
                }
              }
            },
            "innerPadding": {
              "expr": {
                "Literal": {
                  "Value": "36L"
                }
              }
            }
          }
        }
      ],
      "labels": [
        {
          "properties": {
            "show": {
              "expr": {
                "Literal": {
                  "Value": "true"
                }
              }
            },
            "labelPosition": {
              "expr": {
                "Literal": {
                  "Value": "'InsideEnd'"
                }
              }
            },
            "optimizeLabelDisplay": {
              "expr": {
                "Literal": {
                  "Value": "false"
                }
              }
            }
          }
        },
        {
          "properties": {
            "dynamicLabelValue": {
              "expr": {
                "Measure": {
                  "Expression": {
                    "SourceRef": {
                      "Entity": "Measure"
                    }
                  },
                  "Property": "Label Bar City Sales %"
                }
              }
            }
          },
          "selector": {
            "data": [
              {
                "dataViewWildcard": {
                  "matchingOption": 1
                }
              }
            ],
            "highlightMatching": 1
          }
        }
      ]
    },
    "visualContainerObjects": {
      "title": [
        {
          "properties": {
            "show": {
              "expr": {
                "Literal": {
                  "Value": "false"
                }
              }
            }
          }
        }
      ]
    },
    "drillFilterOtherVisuals": true
  },
  "parentGroupName": "5147d92f75e43d7a0abf",
  "filterConfig": {
    "filters": [
      {
        "name": "05ce4ac663189c7d2097",
        "field": {
          "Column": {
            "Expression": {
              "SourceRef": {
                "Entity": "DimPeritos"
              }
            },
            "Property": "PeritoLabel"
          }
        },
        "type": "TopN",
        "filter": {
          "Version": 2,
          "From": [
            {
              "Name": "subquery",
              "Expression": {
                "Subquery": {
                  "Query": {
                    "Version": 2,
                    "From": [
                      {
                        "Name": "o",
                        "Entity": "DimPeritos",
                        "Type": 0
                      }
                    ],
                    "Select": [
                      {
                        "Column": {
                          "Expression": {
                            "SourceRef": {
                              "Source": "o"
                            }
                          },
                          "Property": "PeritoLabel"
                        },
                        "Name": "field"
                      }
                    ],
                    "OrderBy": [
                      {
                        "Direction": 2,
                        "Expression": {
                          "Aggregation": {
                            "Expression": {
                              "Column": {
                                "Expression": {
                                  "SourceRef": {
                                    "Source": "o"
                                  }
                                },
                                "Property": "Sales"
                              }
                            },
                            "Function": 0
                          }
                        }
                      }
                    ],
                    "Top": 5
                  }
                }
              },
              "Type": 2
            },
            {
              "Name": "o",
              "Entity": "DimPeritos",
              "Type": 0
            }
          ],
          "Where": [
            {
              "Condition": {
                "In": {
                  "Expressions": [
                    {
                      "Column": {
                        "Expression": {
                          "SourceRef": {
                            "Source": "o"
                          }
                        },
                        "Property": "PeritoLabel"
                      }
                    }
                  ],
                  "Table": {
                    "SourceRef": {
                      "Source": "subquery"
                    }
                  }
                }
              }
            }
          ]
        }
      }
    ]
  }
}